rct/__init__.py
rct/assignment.py
rct/balance.py
rct/design.py
rct/utils.py
rct/notebooks/examples_k_rerandomized_rct.ipynb
rct/notebooks/examples_quantile_targeting_rct.ipynb
rct/notebooks/examples_rct.ipynb
rct/tests/__init__.py
rct/tests/test_assignment.py
rct/tests/test_balance.py
rct/tests/test_design.py
rct/tests/test_integration.py
rct/tests/test_utils.py
rct/tests/test_data/example_covariates.csv
rct/tests/test_data/krct_2_block_0
rct/tests/test_data/krct_2_block_1
rct/tests/test_data/krct_2_mahalanobis_0
rct/tests/test_data/krct_2_mahalanobis_1
rct/tests/test_data/krct_2_mixed_0
rct/tests/test_data/krct_2_mixed_1
rct/tests/test_data/krct_2_pvalue_0
rct/tests/test_data/krct_2_pvalue_1
rct/tests/test_data/krct_3_block_0
rct/tests/test_data/krct_3_block_1
rct/tests/test_data/krct_3_mahalanobis_0
rct/tests/test_data/krct_3_mahalanobis_1
rct/tests/test_data/krct_3_mixed_0
rct/tests/test_data/krct_3_mixed_1
rct/tests/test_data/krct_3_pvalue_0
rct/tests/test_data/krct_3_pvalue_1
rct/tests/test_data/qrct_2_block_0
rct/tests/test_data/qrct_2_block_1
rct/tests/test_data/qrct_2_mahalanobis_0
rct/tests/test_data/qrct_2_mahalanobis_1
rct/tests/test_data/qrct_2_mixed_0
rct/tests/test_data/qrct_2_mixed_1
rct/tests/test_data/qrct_2_pvalue_0
rct/tests/test_data/qrct_2_pvalue_1
rct/tests/test_data/qrct_3_block_0
rct/tests/test_data/qrct_3_block_1
rct/tests/test_data/qrct_3_mahalanobis_0
rct/tests/test_data/qrct_3_mahalanobis_1
rct/tests/test_data/qrct_3_mixed_0
rct/tests/test_data/qrct_3_mixed_1
rct/tests/test_data/qrct_3_pvalue_0
rct/tests/test_data/qrct_3_pvalue_1
rct/tests/test_data/rct_2_0
rct/tests/test_data/rct_2_1
rct/tests/test_data/rct_3_0
rct/tests/test_data/rct_3_1
rct-0.0.4.dist-info/LICENSE.txt
rct-0.0.4.dist-info/METADATA
rct-0.0.4.dist-info/WHEEL
rct-0.0.4.dist-info/top_level.txt
rct-0.0.4.dist-info/RECORD
