Metadata-Version: 2.1
Name: rct
Version: 0.0.4
Summary: design robust balanced randomized experiments
Home-page: https://github.com/sylvaingchassang/rct
Author: Sylvain Chassang
Author-email: sylvain.chassang@gmail.com
License: UNKNOWN
Keywords: experiment-design RCTs A/B-testing
Platform: UNKNOWN
Classifier: Development Status :: 3 - Alpha
Classifier: Intended Audience :: Science/Research
Classifier: Topic :: Scientific/Engineering
Classifier: Programming Language :: Python :: 3
Classifier: License :: OSI Approved :: MIT License
Classifier: Operating System :: OS Independent
Requires-Python: >=3.6
Requires-Dist: pandas (>=0.25.1)
Requires-Dist: numpy (>=1.17.2)
Requires-Dist: statsmodels (>=0.10.1)
Requires-Dist: parameterized (>=0.7.0)
Requires-Dist: lazy-property (>=0.0.1)
